{
    "Raw_Data_Info": {
        "Acknowledge": "1996",
        "Copyrighter": "㈜미디어그룹사람과숲",
        "Date": "2021-11-14",
        "Equipment": "일반",
        "Exposure_Time": "0.0021551724",
        "F_Stop": "252/100",
        "File_Extension": "mp4",
        "FPS": "30",
        "Inspection_Distance": "100",
        "ISO_ID": "50",
        "Location": "7748681-1",
        "Raw_Data_ID": "S-211114_A_C_2_R_7748681",
        "Resolution": [
            1440,
            1080
        ],
        "Season": "autumn",
        "Structure": "A",
        "Temperature": "8",
        "Time": "15:35:39"
    },
    "Source_Data_Info": {
        "File_Extension": "jpg",
        "Large_ID": "A",
        "Middle_ID": "C",
        "Shooting_ID": "R",
        "Source_Data_ID": "S-211114_A_C_2_R_7748681-1"
    },
    "Learning_Data_Info": {
        "File_Extension": "json",
        "Json_Data_ID": "S-211114_A_C_2_R_7748681-1",
        "Annotations": [
            {
                "Class_ID": "2",
                "Type": "polygon",
                "polygon": [
                    0,
                    218,
                    0,
                    210,
                    28,
                    207,
                    64,
                    197,
                    54,
                    154,
                    41,
                    133,
                    26,
                    80,
                    0,
                    36,
                    0,
                    23,
                    36,
                    79,
                    51,
                    131,
                    64,
                    153,
                    69,
                    188,
                    90,
                    188,
                    95,
                    176,
                    128,
                    175,
                    169,
                    165,
                    191,
                    167,
                    201,
                    178,
                    207,
                    173,
                    256,
                    173,
                    278,
                    164,
                    351,
                    152,
                    389,
                    148,
                    405,
                    143,
                    411,
                    141,
                    433,
                    143,
                    450,
                    136,
                    462,
                    135,
                    469,
                    124,
                    488,
                    131,
                    499,
                    131,
                    507,
                    120,
                    536,
                    118,
                    548,
                    113,
                    567,
                    113,
                    572,
                    108,
                    574,
                    101,
                    581,
                    102,
                    595,
                    95,
                    603,
                    98,
                    613,
                    99,
                    618,
                    94,
                    624,
                    95,
                    620,
                    81,
                    618,
                    67,
                    613,
                    60,
                    613,
                    51,
                    604,
                    27,
                    594,
                    0,
                    599,
                    0,
                    608,
                    19,
                    613,
                    34,
                    621,
                    59,
                    627,
                    88,
                    629,
                    95,
                    635,
                    98,
                    647,
                    98,
                    650,
                    93,
                    656,
                    93,
                    679,
                    77,
                    687,
                    81,
                    697,
                    84,
                    699,
                    78,
                    703,
                    78,
                    702,
                    72,
                    708,
                    72,
                    726,
                    72,
                    730,
                    75,
                    729,
                    70,
                    734,
                    69,
                    740,
                    76,
                    748,
                    72,
                    752,
                    69,
                    759,
                    71,
                    767,
                    66,
                    774,
                    66,
                    778,
                    61,
                    792,
                    58,
                    807,
                    65,
                    813,
                    62,
                    817,
                    63,
                    827,
                    58,
                    829,
                    52,
                    842,
                    51,
                    851,
                    46,
                    856,
                    47,
                    857,
                    52,
                    861,
                    53,
                    868,
                    53,
                    879,
                    53,
                    883,
                    53,
                    885,
                    49,
                    890,
                    46,
                    900,
                    51,
                    896,
                    54,
                    893,
                    53,
                    888,
                    59,
                    879,
                    58,
                    863,
                    58,
                    847,
                    54,
                    836,
                    57,
                    834,
                    64,
                    828,
                    63,
                    828,
                    87,
                    824,
                    86,
                    824,
                    67,
                    817,
                    70,
                    811,
                    69,
                    805,
                    74,
                    798,
                    68,
                    794,
                    67,
                    793,
                    65,
                    780,
                    69,
                    773,
                    72,
                    767,
                    72,
                    759,
                    76,
                    752,
                    75,
                    743,
                    80,
                    736,
                    79,
                    729,
                    78,
                    712,
                    79,
                    700,
                    88,
                    689,
                    90,
                    680,
                    85,
                    676,
                    94,
                    663,
                    96,
                    657,
                    100,
                    644,
                    104,
                    633,
                    103,
                    629,
                    100,
                    622,
                    101,
                    613,
                    106,
                    605,
                    107,
                    595,
                    103,
                    585,
                    107,
                    581,
                    108,
                    575,
                    115,
                    557,
                    120,
                    552,
                    124,
                    548,
                    119,
                    542,
                    126,
                    508,
                    127,
                    507,
                    133,
                    493,
                    138,
                    484,
                    136,
                    472,
                    130,
                    466,
                    142,
                    452,
                    142,
                    438,
                    148,
                    404,
                    150,
                    385,
                    155,
                    371,
                    158,
                    353,
                    159,
                    332,
                    160,
                    327,
                    164,
                    323,
                    163,
                    312,
                    167,
                    306,
                    171,
                    282,
                    171,
                    278,
                    174,
                    267,
                    175,
                    261,
                    179,
                    247,
                    181,
                    211,
                    181,
                    202,
                    184,
                    196,
                    182,
                    186,
                    175,
                    170,
                    173,
                    146,
                    179,
                    124,
                    182,
                    100,
                    184,
                    98,
                    188,
                    95,
                    194,
                    72,
                    194,
                    73,
                    201,
                    61,
                    206,
                    45,
                    211,
                    25,
                    214,
                    19,
                    220,
                    23,
                    233,
                    19,
                    241,
                    20,
                    261,
                    28,
                    276,
                    27,
                    281,
                    35,
                    288,
                    32,
                    334,
                    34,
                    344,
                    38,
                    369,
                    45,
                    377,
                    61,
                    394,
                    65,
                    405,
                    66,
                    411,
                    62,
                    408,
                    57,
                    395,
                    33,
                    372,
                    27,
                    321,
                    28,
                    291,
                    16,
                    269,
                    13,
                    260,
                    14,
                    236,
                    15,
                    230,
                    14,
                    221,
                    16,
                    217
                ]
            },
            {
                "Class_ID": "2",
                "Type": "polygon",
                "polygon": [
                    596,
                    132,
                    599,
                    130,
                    608,
                    150,
                    613,
                    167,
                    618,
                    166,
                    626,
                    160,
                    629,
                    167,
                    634,
                    172,
                    648,
                    175,
                    656,
                    176,
                    657,
                    172,
                    675,
                    170,
                    683,
                    160,
                    694,
                    130,
                    695,
                    125,
                    698,
                    124,
                    696,
                    136,
                    685,
                    162,
                    677,
                    174,
                    672,
                    175,
                    675,
                    183,
                    682,
                    186,
                    690,
                    184,
                    693,
                    176,
                    698,
                    175,
                    710,
                    152,
                    714,
                    150,
                    717,
                    151,
                    718,
                    141,
                    719,
                    128,
                    724,
                    114,
                    727,
                    116,
                    723,
                    130,
                    723,
                    152,
                    719,
                    155,
                    714,
                    156,
                    699,
                    181,
                    694,
                    182,
                    691,
                    191,
                    688,
                    190,
                    682,
                    192,
                    678,
                    190,
                    668,
                    252,
                    663,
                    254,
                    662,
                    250,
                    665,
                    246,
                    673,
                    190,
                    669,
                    184,
                    666,
                    176,
                    654,
                    181,
                    638,
                    180,
                    625,
                    171,
                    624,
                    167,
                    621,
                    172,
                    612,
                    171,
                    608,
                    166
                ]
            },
            {
                "Class_ID": "2",
                "Type": "polygon",
                "polygon": [
                    695,
                    358,
                    696,
                    364,
                    705,
                    352,
                    713,
                    329,
                    716,
                    372,
                    718,
                    378,
                    726,
                    384,
                    738,
                    391,
                    742,
                    389,
                    720,
                    370,
                    716,
                    322,
                    720,
                    308,
                    720,
                    227,
                    722,
                    223,
                    720,
                    213,
                    717,
                    200,
                    715,
                    196,
                    712,
                    196,
                    712,
                    203,
                    716,
                    223,
                    716,
                    303,
                    708,
                    331
                ]
            }
        ]
    }
}