{
    "Raw_Data_Info": {
        "Acknowledge": "1979",
        "Copyrighter": "㈜미디어그룹사람과숲",
        "Date": "2021-09-02",
        "Equipment": "일반",
        "Exposure_Time": "2.910360884749709",
        "F_Stop": "252/100",
        "File_Extension": "mp4",
        "FPS": "30",
        "Inspection_Distance": "102",
        "ISO_ID": "50",
        "Location": "745003-11",
        "Raw_Data_ID": "S-210902_A_C_2_R_4745003",
        "Resolution": [
            1440,
            1080
        ],
        "Season": "summer",
        "Structure": "A",
        "Temperature": "28",
        "Time": "14:38:05"
    },
    "Source_Data_Info": {
        "File_Extension": "jpg",
        "Large_ID": "A",
        "Middle_ID": "C",
        "Shooting_ID": "R",
        "Source_Data_ID": "S-210902_A_C_2_R_4745003-11"
    },
    "Learning_Data_Info": {
        "File_Extension": "json",
        "Json_Data_ID": "S-210902_A_C_2_R_4745003-11",
        "Annotations": [
            {
                "Class_ID": "2",
                "Type": "polygon",
                "polygon": [
                    691,
                    911,
                    693,
                    903,
                    699,
                    893,
                    701,
                    877,
                    706,
                    872,
                    720,
                    866,
                    735,
                    860,
                    741,
                    867,
                    755,
                    874,
                    768,
                    876,
                    778,
                    877,
                    793,
                    874,
                    804,
                    875,
                    812,
                    880,
                    827,
                    886,
                    836,
                    888,
                    855,
                    893,
                    871,
                    888,
                    890,
                    889,
                    902,
                    894,
                    901,
                    899,
                    889,
                    894,
                    878,
                    894,
                    861,
                    897,
                    854,
                    900,
                    849,
                    898,
                    834,
                    892,
                    824,
                    892,
                    815,
                    892,
                    802,
                    882,
                    793,
                    881,
                    774,
                    885,
                    762,
                    882,
                    752,
                    880,
                    740,
                    876,
                    732,
                    868,
                    722,
                    871,
                    713,
                    876,
                    707,
                    880,
                    706,
                    890,
                    702,
                    899,
                    698,
                    909,
                    696,
                    913
                ]
            },
            {
                "Class_ID": "2",
                "Type": "polygon",
                "polygon": [
                    375,
                    1440,
                    387,
                    1401,
                    407,
                    1374,
                    419,
                    1366,
                    422,
                    1370,
                    413,
                    1379,
                    398,
                    1401,
                    382,
                    1440
                ]
            },
            {
                "Class_ID": "2",
                "Type": "polygon",
                "polygon": [
                    301,
                    39,
                    311,
                    31,
                    331,
                    29,
                    344,
                    25,
                    355,
                    23,
                    368,
                    19,
                    378,
                    18,
                    387,
                    21,
                    392,
                    30,
                    394,
                    43,
                    391,
                    45,
                    388,
                    41,
                    385,
                    30,
                    384,
                    38,
                    381,
                    40,
                    380,
                    37,
                    380,
                    24,
                    372,
                    24,
                    364,
                    27,
                    351,
                    30,
                    344,
                    32,
                    334,
                    35,
                    328,
                    37,
                    319,
                    36,
                    310,
                    40,
                    303,
                    43
                ]
            }
        ]
    }
}