{
    "Raw_Data_Info": {
        "Acknowledge": "1977",
        "Copyrighter": "㈜미디어그룹사람과숲",
        "Date": "2021-11-07",
        "Equipment": "일반",
        "Exposure_Time": "0.0017550000",
        "F_Stop": "1800/1000",
        "File_Extension": "mp4",
        "FPS": "30",
        "Inspection_Distance": "112",
        "ISO_ID": "25",
        "Location": "9636070-5",
        "Raw_Data_ID": "S-211107_A_C_3_R_9636070",
        "Resolution": [
            1440,
            1080
        ],
        "Season": "autumn",
        "Structure": "A",
        "Temperature": "14",
        "Time": "14:52:05"
    },
    "Source_Data_Info": {
        "File_Extension": "jpg",
        "Large_ID": "A",
        "Middle_ID": "C",
        "Shooting_ID": "R",
        "Source_Data_ID": "S-211107_A_C_3_R_9636070-5"
    },
    "Learning_Data_Info": {
        "File_Extension": "json",
        "Json_Data_ID": "S-211107_A_C_3_R_9636070-5",
        "Annotations": [
            {
                "Class_ID": "3",
                "Type": "polygon",
                "polygon": [
                    101,
                    471,
                    114,
                    475,
                    127,
                    474,
                    130,
                    473,
                    136,
                    474,
                    141,
                    472,
                    149,
                    477,
                    166,
                    478,
                    175,
                    481,
                    177,
                    489,
                    185,
                    491,
                    194,
                    492,
                    202,
                    489,
                    206,
                    488,
                    210,
                    485,
                    208,
                    480,
                    206,
                    480,
                    205,
                    485,
                    202,
                    488,
                    196,
                    489,
                    190,
                    490,
                    180,
                    487,
                    180,
                    482,
                    195,
                    488,
                    197,
                    486,
                    195,
                    485,
                    182,
                    481,
                    174,
                    477,
                    182,
                    475,
                    185,
                    472,
                    184,
                    471,
                    180,
                    473,
                    175,
                    475,
                    163,
                    476,
                    152,
                    474,
                    143,
                    469,
                    137,
                    471,
                    130,
                    470,
                    122,
                    473,
                    110,
                    472,
                    102,
                    469
                ]
            },
            {
                "Class_ID": "3",
                "Type": "polygon",
                "polygon": [
                    190,
                    476,
                    196,
                    477,
                    206,
                    471,
                    213,
                    474,
                    224,
                    479,
                    234,
                    480,
                    258,
                    492,
                    269,
                    492,
                    278,
                    492,
                    289,
                    499,
                    294,
                    501,
                    292,
                    498,
                    285,
                    492,
                    293,
                    493,
                    304,
                    506,
                    319,
                    517,
                    328,
                    519,
                    328,
                    516,
                    314,
                    509,
                    293,
                    491,
                    282,
                    490,
                    276,
                    486,
                    271,
                    486,
                    274,
                    489,
                    274,
                    490,
                    258,
                    488,
                    241,
                    480,
                    229,
                    477,
                    222,
                    476,
                    215,
                    470,
                    207,
                    469,
                    196,
                    473,
                    192,
                    475
                ]
            },
            {
                "Class_ID": "3",
                "Type": "polygon",
                "polygon": [
                    442,
                    691,
                    465,
                    704,
                    481,
                    706,
                    501,
                    708,
                    511,
                    710,
                    520,
                    718,
                    526,
                    726,
                    517,
                    727,
                    509,
                    730,
                    501,
                    731,
                    494,
                    732,
                    490,
                    727,
                    487,
                    723,
                    483,
                    724,
                    484,
                    727,
                    487,
                    731,
                    463,
                    732,
                    453,
                    737,
                    451,
                    738,
                    444,
                    737,
                    436,
                    740,
                    430,
                    742,
                    423,
                    742,
                    417,
                    745,
                    416,
                    748,
                    423,
                    745,
                    436,
                    743,
                    445,
                    740,
                    450,
                    739,
                    456,
                    740,
                    460,
                    736,
                    475,
                    734,
                    496,
                    734,
                    510,
                    733,
                    519,
                    729,
                    532,
                    729,
                    536,
                    733,
                    538,
                    732,
                    537,
                    730,
                    535,
                    729,
                    533,
                    726,
                    529,
                    724,
                    523,
                    718,
                    527,
                    714,
                    539,
                    722,
                    544,
                    725,
                    551,
                    724,
                    555,
                    722,
                    563,
                    726,
                    563,
                    725,
                    553,
                    721,
                    545,
                    723,
                    535,
                    716,
                    529,
                    713,
                    527,
                    712,
                    531,
                    711,
                    537,
                    713,
                    540,
                    711,
                    538,
                    709,
                    534,
                    710,
                    532,
                    710,
                    530,
                    708,
                    535,
                    706,
                    538,
                    707,
                    540,
                    705,
                    536,
                    703,
                    533,
                    704,
                    528,
                    706,
                    526,
                    710,
                    520,
                    713,
                    519,
                    714,
                    512,
                    708,
                    497,
                    706,
                    472,
                    703,
                    463,
                    700,
                    443,
                    690
                ]
            }
        ]
    }
}